Workbook

Sheet Comece Aqui
A1: ABC INVESTIMENTOS — PLANILHA OFICIAL 50/30/20 & RUMO AO 1º MILHÃO
A2: Guia Rápido de Boas-Vindas • 100% Compatível com Excel, Google Sheets e LibreOffice (Zero Macros)
B4: Etapa | C4: Aba da Planilha | D4: O que fazer / Como funciona | E4: Tempo / Tipo
B5: PASSO 1 | C5: Configuração | D5: Defina sua Renda Líquida Mensal Alvo, sua divisão ideal 50/30/20 e as taxas atuais (Selic, CDI e IPCA). | E5: Leva 2 minutos
B6: PASSO 2 | C6: Lançamentos | D6: Registre suas receitas, gastos essenciais, gastos de estilo de vida e aportes usando os menus suspensos. | E6: Uso diário/semanal
B7: PASSO 3 | C7: Painel do Mês | D7: Acompanhe o termômetro 50/30/20 automático: veja quanto já consumiu de cada grupo e se está na meta. | E7: Automático (SUMIFS)
B8: PASSO 4 | C8: Ano (12 Meses) | D8: Compare Janeiro a Dezembro lado a lado, identifique meses caros e veja sua taxa de aporte anual. | E8: Automático
B9: PASSO 5 | C9: Reserva de Emergência | D9: Descubra sua meta exata de segurança (3, 6 ou 12 meses) e quantos meses faltam para atingir 100%. | E9: Automático + Saldo
B10: PASSO 6 | C10: Metas Financeiras | D10: Planeje objetivos específicos (viagem, carro, entrada de imóvel, estudos) com cálculo do aporte mensal. | E10: Até 10 metas
B11: PASSO 7 | C11: Rumo ao 1º Milhão | D11: Simule sua evolução ano a ano (Patrimônio Nominal vs. Poder de Compra Real descontando IPCA). | E11: Projeção 30 anos
B14: Código de Cores | C14: Significado Visual | D14: Regra de Edição | E14: Proteção
B15: Célula Verde-Clara | C15: Campo de Entrada (Onde você digita seus números) | D15: Pode editar livremente | E15: Desbloqueada
B16: Célula Cinza-Clara | C16: Cálculo Automático (Fórmula integrada) | D16: Não apague (calcula sozinha) | E16: Protegida (sem senha)

Sheet Configuração
A1: CONFIGURAÇÃO PESSOAL & PARÂMETROS ECONÔMICOS (50 / 30 / 20)
A2: Edite apenas as células verdes-claras • Todas as outras abas utilizam estes valores automaticamente
A4: Parâmetro Principal | B4: Valor Atual | C4: Explicação Prática | D4: Categorias Padrão | E4: Subgrupo 50/30/20
A5: Ano Base do Orçamento | B5: 2026 | C5: Ano de referência dos lançamentos | D5: Salário / Pró-labore | E5: Receita
A6: Renda Líquida Mensal Alvo (R$) | B6: 8500 | C6: Sua renda líquida mensal média esperada | D6: Renda Extra / Freelance | E6: Receita
A7: Meta % — Custos Essenciais (50%) | B7: 0.5 | C7: Moradia, mercado, saúde, transporte, contas básicas | D7: Dividendos / Rendimentos | E7: Receita
A8: Meta % — Estilo de Vida / Desejos (30%) | B8: 0.3 | C8: Lazer, restaurantes, streaming, compras pessoais | D8: Moradia (Aluguel/Condomínio) | E8: Essencial (50%)
A9: Meta % — Aportes & Liberdade (20%) | B9: 0.2 | C9: Investimentos mensais + Reserva de Emergência | D9: Supermercado & Feira | E9: Essencial (50%)
A10: Soma das Metas (%) — Deve ser 100% | B10: =SUM(B7:B9) -> 1 | C10: Verificação automática (50% + 30% + 20% = 100%) | D10: Saúde, Farmácia & Plano | E10: Essencial (50%)
A11: Taxa Anual Esperada da Carteira (% a.a.) | B11: 0.12 | C11: Rentabilidade nominal anual estimada (ex.: 12% a.a.) | D11: Transporte / Combustível | E11: Essencial (50%)
A12: Inflação Anual Estimada — IPCA (% a.a.) | B12: 0.045 | C12: Inflação média para cálculo de Poder de Compra Real | D12: Contas (Luz, Água, Internet) | E12: Essencial (50%)
A13: Taxa Real Anual Acima da Inflação (% a.a.) | B13: =((1+B11)/(1+B12))-1 -> 0.071770335 | C13: Fórmula exata de Fisher: (1+Nominal)/(1+IPCA) - 1 | D13: Educação & Cursos | E13: Essencial (50%)
A14: Regra de Retirada Segura Anual (SWR %) | B14: 0.06 | C14: Percentual anual para cálculo de Renda Passiva Mensal | D14: Restaurantes & Delivery | E14: Estilo de Vida (30%)
A15: Meses de Segurança — Reserva de Emergência | B15: 6 | C15: Recomendado: 3 (Servidor), 6 (CLT) ou 12 (Autônomo/PJ) | D15: Lazer, Viagens & Passeios | E15: Estilo de Vida (30%)
A16: Patrimônio Inicial Já Investido (R$) | B16: 25000 | C16: Quanto você já possui acumulado hoje para o 1º Milhão | D16: Assinaturas & Streaming | E16: Estilo de Vida (30%)
A17: Aporte Mensal Planejado Rumo ao Milhão (R$) | B17: =B6*B9 -> 1700 | C17: Calculado automaticamente (Renda Alvo × % Aportes) | D17: Compras Pessoais & Vestuário | E17: Estilo de Vida (30%)
A18: Meta do 1º Milhão (R$) | B18: 1000000 | C18: Valor-alvo da aba Rumo ao 1º Milhão | D18: Aporte Tesouro / Renda Fixa | E18: Aportes (20%)
A19: Status da Configuração | B19: =IF(ROUND(B10,4)=1,"OK — 100% FECHADO","AJUSTAR % PARA SOMAR 100%") -> OK — 100% FECHADO | C19: Confirma se os 3 grupos somam exatamente 100% | D19: Aporte Ações / FIIs / ETFs | E19: Aportes (20%)

Sheet Lançamentos
A1: REGISTRO DE LANÇAMENTOS MENSAIS (RECEITAS, DESPESAS E APORTES)
A2: Preencha Data, Grupo, Categoria, Descrição, Meio e Valor • A coluna Mês (B) calcula sozinha e alimenta os Painéis
A4: Data | B4: Mês (Auto) | C4: Grupo 50/30/20 | D4: Categoria | E4: Descrição do Lançamento | F4: Conta / Meio | G4: Valor (R$) | H4: Status
A5: 46027.5 | B5: =IF(ISNUMBER(A5),MONTH(A5),"") -> 1 | C5: Receita | D5: Salário / Pró-labore | E5: Salário Mensal Líquido | F5: PIX / Conta | G5: 8200 | H5: Pago
A6: 46029.5 | B6: =IF(ISNUMBER(A6),MONTH(A6),"") -> 1 | C6: Essencial (50%) | D6: Moradia (Aluguel/Condomínio) | E6: Aluguel + Condomínio | F6: Boleto | G6: 2250 | H6: Pago
A7: 46032.5 | B7: =IF(ISNUMBER(A7),MONTH(A7),"") -> 1 | C7: Essencial (50%) | D7: Supermercado & Feira | E7: Compras do Mês Atacadista | F7: Cartão Crédito | G7: 1180 | H7: Pago
A8: 46034.5 | B8: =IF(ISNUMBER(A8),MONTH(A8),"") -> 1 | C8: Essencial (50%) | D8: Contas (Luz, Água, Internet) | E8: Energia + Fibra Óptica | F8: Débito Automático | G8: 390 | H8: Pago
A9: 46037.5 | B9: =IF(ISNUMBER(A9),MONTH(A9),"") -> 1 | C9: Estilo de Vida (30%) | D9: Restaurantes & Delivery | E9: Jantar de fim de semana | F9: Cartão Crédito | G9: 460 | H9: Pago
A10: 46040.5 | B10: =IF(ISNUMBER(A10),MONTH(A10),"") -> 1 | C10: Estilo de Vida (30%) | D10: Assinaturas & Streaming | E10: Streaming + Academia | F10: Cartão Crédito | G10: 240 | H10: Pago
A11: 46042.5 | B11: =IF(ISNUMBER(A11),MONTH(A11),"") -> 1 | C11: Aportes (20%) | D11: Aporte Tesouro / Renda Fixa | E11: Aporte Tesouro Selic Reserva | F11: Corretora | G11: 1200 | H11: Pago
A12: 46044.5 | B12: =IF(ISNUMBER(A12),MONTH(A12),"") -> 1 | C12: Aportes (20%) | D12: Aporte Ações / FIIs / ETFs | E12: Compra de FIIs e Ações Dividendos | F12: Corretora | G12: 650 | H12: Pago
B13: =IF(ISNUMBER(A13),MONTH(A13),"")
B14: =IF(ISNUMBER(A14),MONTH(A14),"")
B15: =IF(ISNUMBER(A15),MONTH(A15),"")
B16: =IF(ISNUMBER(A16),MONTH(A16),"")
B17: =IF(ISNUMBER(A17),MONTH(A17),"")
B18: =IF(ISNUMBER(A18),MONTH(A18),"")
B19: =IF(ISNUMBER(A19),MONTH(A19),"")
B20: =IF(ISNUMBER(A20),MONTH(A20),"")
B21: =IF(ISNUMBER(A21),MONTH(A21),"")
B22: =IF(ISNUMBER(A22),MONTH(A22),"")
B23: =IF(ISNUMBER(A23),MONTH(A23),"")
B24: =IF(ISNUMBER(A24),MONTH(A24),"")
... B124: =IF(ISNUMBER(A124),MONTH(A124),"")

Sheet Painel do Mês
A1: PAINEL EXECUTIVO DO MÊS — TERMÔMETRO 50 / 30 / 20
A2: Selecione o número do mês (1 a 12) na célula B4 • Todos os indicadores abaixo são calculados automaticamente
A4: Mês Selecionado para Análise (1 a 12): | B4: 1 | C4: Receita Realizada no Mês: | D4: =SUMIFS(Lançamentos!G$5:G$124,Lançamentos!B$5:B$124,B4,Lançamentos!C$5:C$124,"Receita") -> 8200 | E4: Saldo Livre em Caixa: | F4: =D4-SUM(C7:C9) -> 1830
A6: Bloco do Método 50/30/20 | B6: Meta Orçada (R$) | C6: Valor Realizado (R$) | D6: % da Receita Real | E6: Diferença (R$) | F6: Diagnóstico Automático
A7: Essencial (50%) | B7: =MAX($D$4,Configuração!B6)*Configuração!B7 -> 4250 | C7: =SUMIFS(Lançamentos!G$5:G$124,Lançamentos!B$5:B$124,$B$4,Lançamentos!C$5:C$124,A7) -> 3820 | D7: =IF($D$4>0,C7/$D$4,0) -> 0.46585366 | E7: =B7-C7 -> 430 | F7: =IF(C7<=B7,"DENTRO DO ORÇAMENTO","ACIMA DO LIMITE") -> DENTRO DO ORÇAMENTO
A8: Estilo de Vida (30%) | B8: =MAX($D$4,Configuração!B6)*Configuração!B8 -> 2550 | C8: =SUMIFS(Lançamentos!G$5:G$124,Lançamentos!B$5:B$124,$B$4,Lançamentos!C$5:C$124,A8) -> 700 | D8: =IF($D$4>0,C8/$D$4,0) -> 0.085365854 | E8: =B8-C8 -> 1850 | F8: =IF(C8<=B8,"DENTRO DO ORÇAMENTO","ACIMA DO LIMITE") -> DENTRO DO ORÇAMENTO
A9: Aportes (20%) | B9: =MAX($D$4,Configuração!B6)*Configuração!B9 -> 1700 | C9: =SUMIFS(Lançamentos!G$5:G$124,Lançamentos!B$5:B$124,$B$4,Lançamentos!C$5:C$124,A9) -> 1850 | D9: =IF($D$4>0,C9/$D$4,0) -> 0.22560976 | E9: =B9-C9 -> -150 | F9: =IF(C9>=B9,"META DE APORTE BATIDA!","Aporte abaixo da meta") -> META DE APORTE BATIDA!
A10: TOTAL ALOCADO NO MÊS | B10: =SUM(B7:B9) -> 8500 | C10: =SUM(C7:C9) -> 6370 | D10: =SUM(D7:D9) -> 0.77682927 | E10: =SUM(E7:E9) -> 2130 | F10: =IF(D4>=C10,"SUPERÁVIT NO MÊS","DÉFICIT NO MÊS") -> SUPERÁVIT NO MÊS

Sheet Ano (12 Meses)
A1: VISÃO CONSOLIDADA ANUAL (JANEIRO A DEZEMBRO) + MÉDIA E ACUMULADO
A2: Todos os meses são preenchidos automaticamente a partir da aba Lançamentos
A3: Nº do Mês | B3: 1 | C3: 2 | D3: 3 | E3: 4 | F3: 5 | G3: 6 | H3: 7 | I3: 8 | J3: 9 | K3: 10 | L3: 11 | M3: 12 | N3: Acumulado | O3: Média
A4: Grupo / Indicador | B4: Jan | C4: Fev | D4: Mar | E4: Abr | F4: Mai | G4: Jun | H4: Jul | I4: Ago | J4: Set | K4: Out | L4: Nov | M4: Dez | N4: Total Ano | O4: Média Mensal
A5: Receita | B5: =SUMIFS(Lançamentos!$G$5:$G$124,Lançamentos!$B$5:$B$124,B$3,Lançamentos!$C$5:$C$124,$A5) -> 8200 | C5: =SUMIFS(Lançamentos!$G$5:$G$124,Lançamentos!$B$5:$B$124,C$3,Lançamentos!$C$5:$C$124,$A5) -> 0 | D5: =SUMIFS(Lançamentos!$G$5:$G$124,Lançamentos!$B$5:$B$124,D$3,Lançamentos!$C$5:$C$124,$A5) -> 0 | E5: =SUMIFS(Lançamentos!$G$5:$G$124,Lançamentos!$B$5:$B$124,E$3,Lançamentos!$C$5:$C$124,$A5) -> 0 | F5: =SUMIFS(Lançamentos!$G$5:$G$124,Lançamentos!$B$5:$B$124,F$3,Lançamentos!$C$5:$C$124,$A5) -> 0 | G5: =SUMIFS(Lançamentos!$G$5:$G$124,Lançamentos!$B$5:$B$124,G$3,Lançamentos!$C$5:$C$124,$A5) -> 0 | H5: =SUMIFS(Lançamentos!$G$5:$G$124,Lançamentos!$B$5:$B$124,H$3,Lançamentos!$C$5:$C$124,$A5) -> 0 | I5: =SUMIFS(Lançamentos!$G$5:$G$124,Lançamentos!$B$5:$B$124,I$3,Lançamentos!$C$5:$C$124,$A5) -> 0 | ... M5: =SUMIFS(Lançamentos!$G$5:$G$124,Lançamentos!$B$5:$B$124,M$3,Lançamentos!$C$5:$C$124,$A5) -> 0 | N5: =SUM(B5:M5) -> 8200 | O5: =AVERAGE(B5:M5) -> 683.33333
A6: Essencial (50%) | B6: =SUMIFS(Lançamentos!$G$5:$G$124,Lançamentos!$B$5:$B$124,B$3,Lançamentos!$C$5:$C$124,$A6) -> 3820 | C6: =SUMIFS(Lançamentos!$G$5:$G$124,Lançamentos!$B$5:$B$124,C$3,Lançamentos!$C$5:$C$124,$A6) -> 0 | D6: =SUMIFS(Lançamentos!$G$5:$G$124,Lançamentos!$B$5:$B$124,D$3,Lançamentos!$C$5:$C$124,$A6) -> 0 | E6: =SUMIFS(Lançamentos!$G$5:$G$124,Lançamentos!$B$5:$B$124,E$3,Lançamentos!$C$5:$C$124,$A6) -> 0 | F6: =SUMIFS(Lançamentos!$G$5:$G$124,Lançamentos!$B$5:$B$124,F$3,Lançamentos!$C$5:$C$124,$A6) -> 0 | G6: =SUMIFS(Lançamentos!$G$5:$G$124,Lançamentos!$B$5:$B$124,G$3,Lançamentos!$C$5:$C$124,$A6) -> 0 | H6: =SUMIFS(Lançamentos!$G$5:$G$124,Lançamentos!$B$5:$B$124,H$3,Lançamentos!$C$5:$C$124,$A6) -> 0 | I6: =SUMIFS(Lançamentos!$G$5:$G$124,Lançamentos!$B$5:$B$124,I$3,Lançamentos!$C$5:$C$124,$A6) -> 0 | ... M6: =SUMIFS(Lançamentos!$G$5:$G$124,Lançamentos!$B$5:$B$124,M$3,Lançamentos!$C$5:$C$124,$A6) -> 0 | N6: =SUM(B6:M6) -> 3820 | O6: =AVERAGE(B6:M6) -> 318.33333
A7: Estilo de Vida (30%) | B7: =SUMIFS(Lançamentos!$G$5:$G$124,Lançamentos!$B$5:$B$124,B$3,Lançamentos!$C$5:$C$124,$A7) -> 700 | C7: =SUMIFS(Lançamentos!$G$5:$G$124,Lançamentos!$B$5:$B$124,C$3,Lançamentos!$C$5:$C$124,$A7) -> 0 | D7: =SUMIFS(Lançamentos!$G$5:$G$124,Lançamentos!$B$5:$B$124,D$3,Lançamentos!$C$5:$C$124,$A7) -> 0 | E7: =SUMIFS(Lançamentos!$G$5:$G$124,Lançamentos!$B$5:$B$124,E$3,Lançamentos!$C$5:$C$124,$A7) -> 0 | F7: =SUMIFS(Lançamentos!$G$5:$G$124,Lançamentos!$B$5:$B$124,F$3,Lançamentos!$C$5:$C$124,$A7) -> 0 | G7: =SUMIFS(Lançamentos!$G$5:$G$124,Lançamentos!$B$5:$B$124,G$3,Lançamentos!$C$5:$C$124,$A7) -> 0 | H7: =SUMIFS(Lançamentos!$G$5:$G$124,Lançamentos!$B$5:$B$124,H$3,Lançamentos!$C$5:$C$124,$A7) -> 0 | I7: =SUMIFS(Lançamentos!$G$5:$G$124,Lançamentos!$B$5:$B$124,I$3,Lançamentos!$C$5:$C$124,$A7) -> 0 | ... M7: =SUMIFS(Lançamentos!$G$5:$G$124,Lançamentos!$B$5:$B$124,M$3,Lançamentos!$C$5:$C$124,$A7) -> 0 | N7: =SUM(B7:M7) -> 700 | O7: =AVERAGE(B7:M7) -> 58.333333
A8: Aportes (20%) | B8: =SUMIFS(Lançamentos!$G$5:$G$124,Lançamentos!$B$5:$B$124,B$3,Lançamentos!$C$5:$C$124,$A8) -> 1850 | C8: =SUMIFS(Lançamentos!$G$5:$G$124,Lançamentos!$B$5:$B$124,C$3,Lançamentos!$C$5:$C$124,$A8) -> 0 | D8: =SUMIFS(Lançamentos!$G$5:$G$124,Lançamentos!$B$5:$B$124,D$3,Lançamentos!$C$5:$C$124,$A8) -> 0 | E8: =SUMIFS(Lançamentos!$G$5:$G$124,Lançamentos!$B$5:$B$124,E$3,Lançamentos!$C$5:$C$124,$A8) -> 0 | F8: =SUMIFS(Lançamentos!$G$5:$G$124,Lançamentos!$B$5:$B$124,F$3,Lançamentos!$C$5:$C$124,$A8) -> 0 | G8: =SUMIFS(Lançamentos!$G$5:$G$124,Lançamentos!$B$5:$B$124,G$3,Lançamentos!$C$5:$C$124,$A8) -> 0 | H8: =SUMIFS(Lançamentos!$G$5:$G$124,Lançamentos!$B$5:$B$124,H$3,Lançamentos!$C$5:$C$124,$A8) -> 0 | I8: =SUMIFS(Lançamentos!$G$5:$G$124,Lançamentos!$B$5:$B$124,I$3,Lançamentos!$C$5:$C$124,$A8) -> 0 | ... M8: =SUMIFS(Lançamentos!$G$5:$G$124,Lançamentos!$B$5:$B$124,M$3,Lançamentos!$C$5:$C$124,$A8) -> 0 | N8: =SUM(B8:M8) -> 1850 | O8: =AVERAGE(B8:M8) -> 154.16667
A9: Saldo Livre de Caixa (R$) | B9: =B5-B6-B7-B8 -> 1830 | C9: =C5-C6-C7-C8 -> 0 | D9: =D5-D6-D7-D8 -> 0 | E9: =E5-E6-E7-E8 -> 0 | F9: =F5-F6-F7-F8 -> 0 | G9: =G5-G6-G7-G8 -> 0 | H9: =H5-H6-H7-H8 -> 0 | I9: =I5-I6-I7-I8 -> 0 | ... M9: =M5-M6-M7-M8 -> 0 | N9: =SUM(B9:M9) -> 1830 | O9: =AVERAGE(B9:M9) -> 152.5
A10: Taxa de Aporte Mensal (%) | B10: =IF(B5>0,B8/B5,0) -> 0.22560976 | C10: =IF(C5>0,C8/C5,0) -> 0 | D10: =IF(D5>0,D8/D5,0) -> 0 | E10: =IF(E5>0,E8/E5,0) -> 0 | F10: =IF(F5>0,F8/F5,0) -> 0 | G10: =IF(G5>0,G8/G5,0) -> 0 | H10: =IF(H5>0,H8/H5,0) -> 0 | I10: =IF(I5>0,I8/I5,0) -> 0 | ... O10: =IF(O5>0,O8/O5,0) -> 0.22560976

Sheet Reserva de Emergência
A1: CALCULADORA & RASTREADOR DA RESERVA DE EMERGÊNCIA
A2: Dimensione seu colchão de segurança em Tesouro Selic ou CDB 100% CDI com liquidez diária
A4: Indicador da Reserva de Emergência | B4: Valor / Resultado | C4: Orientação Técnica
A5: Seu Custo Mensal Essencial Médio (R$) | B5: 4250 | C5: Soma de moradia, alimentação, saúde, transporte e contas fixas
A6: Meses de Segurança Recomendados | B6: =Configuração!B15 -> 6 | C6: Puxado da aba Configuração (3 = Servidor, 6 = CLT, 12 = Autônomo/PJ)
A7: META TOTAL DA SUA RESERVA (R$) | B7: =B5*B6 -> 25500 | C7: Valor total que traz paz de espírito para sua família
A8: Saldo Atual Já Guardado na Reserva (R$) | B8: 12000 | C8: Some apenas aplicações de Liquidez Diária (Tesouro Selic / CDB 100% CDI)
A9: Percentual Concluído da Reserva (%) | B9: =IF(B7>0,MIN(1,B8/B7),0) -> 0.47058824 | C9: Progresso rumo a 100% da sua Reserva de Emergência
A10: Valor que Ainda Falta Acumular (R$) | B10: =MAX(0,B7-B8) -> 13500 | C10: Diferença entre a Meta Total e o Saldo Atual
A11: Aporte Mensal Dedicado à Reserva (R$) | B11: 1000 | C11: Quanto você vai destinar por mês até completar a Reserva
A12: Meses Estimados para Concluir 100% | B12: =IF(B10<=0,0,IF(B11>0,B10/B11,0)) -> 13.5 | C12: Tempo aproximado (sem contar os juros compostos do Tesouro Selic a seu favor)
A13: Status da Reserva de Segurança | B13: =IF(B8>=B7,"RESERVA 100% COMPLETA!","EM CONSTRUÇÃO — PRIORIDADE Nº 1") -> EM CONSTRUÇÃO — PRIORIDADE Nº 1 | C13: Complete a Reserva antes de investir em renda variável

Sheet Metas Financeiras
A1: PLANEJADOR DE METAS FINANCEIRAS (CURTO E MÉDIO PRAZO)
A2: Planeje viagens, troca de veículo, entrada de imóvel ou equipamentos sem entrar em financiamentos caros
A4: Nome do Objetivo / Meta | B4: Prioridade | C4: Valor-Alvo (R$) | D4: Valor Já Guardado (R$) | E4: Prazo (Meses) | F4: Falta Acumular (R$) | G4: % Concluído | H4: Aporte Mensal Necessário
A5: Viagem de Férias em Família | B5: Alta | C5: 12000 | D5: 4500 | E5: 10 | F5: =MAX(0,C5-D5) -> 7500 | G5: =IF(C5>0,D5/C5,0) -> 0.375 | H5: =IF(E5>0,F5/E5,0) -> 750
A6: Troca de Notebook / Setup Trabalho | B6: Média | C6: 7500 | D6: 3000 | E6: 6 | F6: =MAX(0,C6-D6) -> 4500 | G6: =IF(C6>0,D6/C6,0) -> 0.4 | H6: =IF(E6>0,F6/E6,0) -> 750
A7: Entrada Apartamento / Amortização | B7: Alta | C7: 60000 | D7: 18000 | E7: 24 | F7: =MAX(0,C7-D7) -> 42000 | G7: =IF(C7>0,D7/C7,0) -> 0.3 | H7: =IF(E7>0,F7/E7,0) -> 1750
A8: Fundo Anual IPVA + IPTU + Seguros | B8: Alta | C8: 6000 | D8: 2400 | E8: 8 | F8: =MAX(0,C8-D8) -> 3600 | G8: =IF(C8>0,D8/C8,0) -> 0.4 | H8: =IF(E8>0,F8/E8,0) -> 450
A9: Pós-Graduação / Certificação | B9: Média | C9: 9000 | D9: 1500 | E9: 12 | F9: =MAX(0,C9-D9) -> 7500 | G9: =IF(C9>0,D9/C9,0) -> 0.16666667 | H9: =IF(E9>0,F9/E9,0) -> 625
C10: 0 | D10: 0 | E10: 12 | F10: =MAX(0,C10-D10) -> 0 | G10: =IF(C10>0,D10/C10,0) -> 0 | H10: =IF(E10>0,F10/E10,0) -> 0
C11: 0 | D11: 0 | E11: 12 | F11: =MAX(0,C11-D11) -> 0 | G11: =IF(C11>0,D11/C11,0) -> 0 | H11: =IF(E11>0,F11/E11,0) -> 0
C12: 0 | D12: 0 | E12: 12 | F12: =MAX(0,C12-D12) -> 0 | G12: =IF(C12>0,D12/C12,0) -> 0 | H12: =IF(E12>0,F12/E12,0) -> 0
C13: 0 | D13: 0 | E13: 12 | F13: =MAX(0,C13-D13) -> 0 | G13: =IF(C13>0,D13/C13,0) -> 0 | H13: =IF(E13>0,F13/E13,0) -> 0
C14: 0 | D14: 0 | E14: 12 | F14: =MAX(0,C14-D14) -> 0 | G14: =IF(C14>0,D14/C14,0) -> 0 | H14: =IF(E14>0,F14/E14,0) -> 0

Sheet Rumo ao 1º Milhão
A1: SIMULADOR DE INDEPENDÊNCIA FINANCEIRA — RUMO AO 1º MILHÃO (30 ANOS)
A2: Projeção anual baseada no Patrimônio Inicial, Aporte Mensal e Taxas definidas na aba Configuração
A4: Inicial: | B4: =Configuração!B16 -> 25000 | C4: Aporte Mensal: | D4: =Configuração!B17 -> 1700 | E4: Taxa Nominal a.a.: | F4: =Configuração!B11 -> 0.12 | G4: Taxa Real (pós-IPCA): | H4: =Configuração!B13 -> 0.071770335
A5: Ano # | B5: Ano Civil | C5: Total Investido do Bolso | D5: Patrimônio Nominal (R$) | E5: Juros Acumulados (R$) | F5: Patrimônio Real (Pós-IPCA) | G5: Renda Passiva Mensal | H5: Status da Meta (R$ 1M)
A6: 1 | B6: =Configuração!$B$5+A6 -> 2027 | C6: =Configuração!$B$16+(Configuração!$B$17*12*A6) -> 45400 | D6: =Configuração!$B$16*(1+Configuração!$B$11)+(Configuração!$B$17*12) -> 48400 | E6: =D6-C6 -> 3000 | F6: =Configuração!$B$16*(1+Configuração!$B$13)+(Configuração!$B$17*12) -> 47194.258 | G6: =(F6*Configuração!$B$14)/12 -> 235.97129 | H6: =IF(D6>=Configuração!$B$18,"1º MILHÃO ALCANÇADO!","Acumulando...") -> Acumulando...
A7: 2 | B7: =Configuração!$B$5+A7 -> 2028 | C7: =Configuração!$B$16+(Configuração!$B$17*12*A7) -> 65800 | D7: =D6*(1+Configuração!$B$11)+(Configuração!$B$17*12) -> 74608 | E7: =D7-C7 -> 8808 | F7: =F6*(1+Configuração!$B$13)+(Configuração!$B$17*12) -> 70981.406 | G7: =(F7*Configuração!$B$14)/12 -> 354.90703 | H7: =IF(D7>=Configuração!$B$18,"1º MILHÃO ALCANÇADO!","Acumulando...") -> Acumulando...
A8: 3 | B8: =Configuração!$B$5+A8 -> 2029 | C8: =Configuração!$B$16+(Configuração!$B$17*12*A8) -> 86200 | D8: =D7*(1+Configuração!$B$11)+(Configuração!$B$17*12) -> 103960.96 | E8: =D8-C8 -> 17760.96 | F8: =F7*(1+Configuração!$B$13)+(Configuração!$B$17*12) -> 96475.765 | G8: =(F8*Configuração!$B$14)/12 -> 482.37883 | H8: =IF(D8>=Configuração!$B$18,"1º MILHÃO ALCANÇADO!","Acumulando...") -> Acumulando...
A9: 4 | B9: =Configuração!$B$5+A9 -> 2030 | C9: =Configuração!$B$16+(Configuração!$B$17*12*A9) -> 106600 | D9: =D8*(1+Configuração!$B$11)+(Configuração!$B$17*12) -> 136836.28 | E9: =D9-C9 -> 30236.275 | F9: =F8*(1+Configuração!$B$13)+(Configuração!$B$17*12) -> 123799.86 | G9: =(F9*Configuração!$B$14)/12 -> 618.99932 | H9: =IF(D9>=Configuração!$B$18,"1º MILHÃO ALCANÇADO!","Acumulando...") -> Acumulando...
A10: 5 | B10: =Configuração!$B$5+A10 -> 2031 | C10: =Configuração!$B$16+(Configuração!$B$17*12*A10) -> 127000 | D10: =D9*(1+Configuração!$B$11)+(Configuração!$B$17*12) -> 173656.63 | E10: =D10-C10 -> 46656.628 | F10: =F9*(1+Configuração!$B$13)+(Configuração!$B$17*12) -> 153085.02 | G10: =(F10*Configuração!$B$14)/12 -> 765.42511 | H10: =IF(D10>=Configuração!$B$18,"1º MILHÃO ALCANÇADO!","Acumulando...") -> Acumulando...
A11: 6 | B11: =Configuração!$B$5+A11 -> 2032 | C11: =Configuração!$B$16+(Configuração!$B$17*12*A11) -> 147400 | D11: =D10*(1+Configuração!$B$11)+(Configuração!$B$17*12) -> 214895.42 | E11: =D11-C11 -> 67495.424 | F11: =F10*(1+Configuração!$B$13)+(Configuração!$B$17*12) -> 184471.98 | G11: =(F11*Configuração!$B$14)/12 -> 922.35992 | H11: =IF(D11>=Configuração!$B$18,"1º MILHÃO ALCANÇADO!","Acumulando...") -> Acumulando...
A12: 7 | B12: =Configuração!$B$5+A12 -> 2033 | C12: =Configuração!$B$16+(Configuração!$B$17*12*A12) -> 167800 | D12: =D11*(1+Configuração!$B$11)+(Configuração!$B$17*12) -> 261082.87 | E12: =D12-C12 -> 93282.874 | F12: =F11*(1+Configuração!$B$13)+(Configuração!$B$17*12) -> 218111.6 | G12: =(F12*Configuração!$B$14)/12 -> 1090.558 | H12: =IF(D12>=Configuração!$B$18,"1º MILHÃO ALCANÇADO!","Acumulando...") -> Acumulando...
A13: 8 | B13: =Configuração!$B$5+A13 -> 2034 | C13: =Configuração!$B$16+(Configuração!$B$17*12*A13) -> 188200 | D13: =D12*(1+Configuração!$B$11)+(Configuração!$B$17*12) -> 312812.82 | E13: =D13-C13 -> 124612.82 | F13: =F12*(1+Configuração!$B$13)+(Configuração!$B$17*12) -> 254165.54 | G13: =(F13*Configuração!$B$14)/12 -> 1270.8277 | H13: =IF(D13>=Configuração!$B$18,"1º MILHÃO ALCANÇADO!","Acumulando...") -> Acumulando...
A14: 9 | B14: =Configuração!$B$5+A14 -> 2035 | C14: =Configuração!$B$16+(Configuração!$B$17*12*A14) -> 208600 | D14: =D13*(1+Configuração!$B$11)+(Configuração!$B$17*12) -> 370750.36 | E14: =D14-C14 -> 162150.36 | F14: =F13*(1+Configuração!$B$13)+(Configuração!$B$17*12) -> 292807.09 | G14: =(F14*Configuração!$B$14)/12 -> 1464.0354 | H14: =IF(D14>=Configuração!$B$18,"1º MILHÃO ALCANÇADO!","Acumulando...") -> Acumulando...
A15: 10 | B15: =Configuração!$B$5+A15 -> 2036 | C15: =Configuração!$B$16+(Configuração!$B$17*12*A15) -> 229000 | D15: =D14*(1+Configuração!$B$11)+(Configuração!$B$17*12) -> 435640.4 | E15: =D15-C15 -> 206640.4 | F15: =F14*(1+Configuração!$B$13)+(Configuração!$B$17*12) -> 334221.95 | G15: =(F15*Configuração!$B$14)/12 -> 1671.1098 | H15: =IF(D15>=Configuração!$B$18,"1º MILHÃO ALCANÇADO!","Acumulando...") -> Acumulando...
A16: 11 | B16: =Configuração!$B$5+A16 -> 2037 | C16: =Configuração!$B$16+(Configuração!$B$17*12*A16) -> 249400 | D16: =D15*(1+Configuração!$B$11)+(Configuração!$B$17*12) -> 508317.25 | E16: =D16-C16 -> 258917.25 | F16: =F15*(1+Configuração!$B$13)+(Configuração!$B$17*12) -> 378609.17 | G16: =(F16*Configuração!$B$14)/12 -> 1893.0459 | H16: =IF(D16>=Configuração!$B$18,"1º MILHÃO ALCANÇADO!","Acumulando...") -> Acumulando...
A17: 12 | B17: =Configuração!$B$5+A17 -> 2038 | C17: =Configuração!$B$16+(Configuração!$B$17*12*A17) -> 269800 | D17: =D16*(1+Configuração!$B$11)+(Configuração!$B$17*12) -> 589715.32 | E17: =D17-C17 -> 319915.32 | F17: =F16*(1+Configuração!$B$13)+(Configuração!$B$17*12) -> 426182.08 | G17: =(F17*Configuração!$B$14)/12 -> 2130.9104 | H17: =IF(D17>=Configuração!$B$18,"1º MILHÃO ALCANÇADO!","Acumulando...") -> Acumulando...
A18: 13 | B18: =Configuração!$B$5+A18 -> 2039 | C18: =Configuração!$B$16+(Configuração!$B$17*12*A18) -> 290200 | D18: =D17*(1+Configuração!$B$11)+(Configuração!$B$17*12) -> 680881.16 | E18: =D18-C18 -> 390681.16 | F18: =F17*(1+Configuração!$B$13)+(Configuração!$B$17*12) -> 477169.31 | G18: =(F18*Configuração!$B$14)/12 -> 2385.8466 | H18: =IF(D18>=Configuração!$B$18,"1º MILHÃO ALCANÇADO!","Acumulando...") -> Acumulando...
... A35: 30 | B35: =Configuração!$B$5+A35 -> 2056 | C35: =Configuração!$B$16+(Configuração!$B$17*12*A35) -> 637000 | D35: =D34*(1+Configuração!$B$11)+(Configuração!$B$17*12) -> 5672184.8 | E35: =D35-C35 -> 5035184.8 | F35: =F34*(1+Configuração!$B$13)+(Configuração!$B$17*12) -> 2189463.4 | G35: =(F35*Configuração!$B$14)/12 -> 10947.317 | H35: =IF(D35>=Configuração!$B$18,"1º MILHÃO ALCANÇADO!","Acumulando...") -> 1º MILHÃO ALCANÇADO!
